routegym/__init__.py
routegym/env.py
routegym/graph.py
routegym/train.py
routegym/validate.py
route_gym-0.0.11.dist-info/METADATA
route_gym-0.0.11.dist-info/WHEEL
route_gym-0.0.11.dist-info/top_level.txt
route_gym-0.0.11.dist-info/RECORD
