Metadata-Version: 2.1
Name: route-gym
Version: 0.0.11
Summary: RL environment for solving shortest or longest route problems
Home-page: https://github.com/Velythyl/route-gym
Author: Charlie Gauthier
Author-email: charlie.gauthier@umontreal.ca
License: MIT
Platform: UNKNOWN
Classifier: License :: OSI Approved :: MIT License
Classifier: Programming Language :: Python :: 3
Classifier: Programming Language :: Python :: 3.7
Requires-Dist: matplotlib
Requires-Dist: networkx
Requires-Dist: numpy
Requires-Dist: pyglet
Requires-Dist: pymdptoolbox
